__init__.py
consts.py
hikaxpro.py
errors/errors.py
helpers/__init__.py
helpers/sha256.py
helpers/xmlBuilder.py
models/SessionLogin.py
models/SessionLoginCap.py
models/__init__.py
hikaxpro-2.3.0.dist-info/LICENSE
hikaxpro-2.3.0.dist-info/METADATA
hikaxpro-2.3.0.dist-info/WHEEL
hikaxpro-2.3.0.dist-info/top_level.txt
hikaxpro-2.3.0.dist-info/RECORD
