Metadata-Version: 2.1
Name: hikaxpro
Version: 2.3.0
Summary: Hikvision AX Pro alarm kit ISAPI integration for home assistant alarm panel
Author-email: Günkut Zeybek <gunkut.zeybek@gmail.com>, Petr Leo Compel <petrleocompel@gmail.com>
License: The MIT License (MIT)
Project-URL: repository, https://github.com/petrleocompel/hikaxpro/
Keywords: hikvision,ISAPI,homeassistant
Classifier: License :: OSI Approved :: MIT License
Classifier: Programming Language :: Python
Classifier: Programming Language :: Python :: 3
Requires-Python: >=3.9
License-File: LICENSE
Requires-Dist: requests
Provides-Extra: dev
Requires-Dist: pytest; extra == "dev"
Requires-Dist: requests-mock; extra == "dev"
